mkdocs_asy.py
mkdocs_asy-1.1.dist-info/LICENSE
mkdocs_asy-1.1.dist-info/METADATA
mkdocs_asy-1.1.dist-info/WHEEL
mkdocs_asy-1.1.dist-info/top_level.txt
mkdocs_asy-1.1.dist-info/RECORD
